pkgevents/__init__.py
pkgevents/cc.py
pkgevents-0.0.5.dist-info/LICENSE.txt
pkgevents-0.0.5.dist-info/METADATA
pkgevents-0.0.5.dist-info/WHEEL
pkgevents-0.0.5.dist-info/top_level.txt
pkgevents-0.0.5.dist-info/RECORD
