Metadata-Version: 2.1
Name: pkgevents
Version: 0.0.5
Summary: An event package for making packages
Home-page: https://github.com/thatrandomperson5/pkgEvents
Author: DragonHunter
Author-email: 
License: UNKNOWN
Project-URL: Bug Tracker, https://github.com/thatrandomperson5/pkgEvents/issues
Platform: UNKNOWN
Classifier: Programming Language :: Python :: 3
Classifier: License :: OSI Approved :: MIT License
Classifier: Operating System :: OS Independent
Requires-Python: >=3.6
License-File: LICENSE.txt
